aniffinity/__about__.py
aniffinity/__init__.py
aniffinity/aniffinity.py
aniffinity/calcs.py
aniffinity/const.py
aniffinity/endpoints.py
aniffinity/exceptions.py
aniffinity/models.py
aniffinity/resolver.py
aniffinity-0.2.0.dist-info/LICENSE
aniffinity-0.2.0.dist-info/METADATA
aniffinity-0.2.0.dist-info/WHEEL
aniffinity-0.2.0.dist-info/top_level.txt
aniffinity-0.2.0.dist-info/RECORD
