Metadata-Version: 2.1
Name: aniffinity
Version: 0.2.0
Summary: Calculate affinity between anime list users
Home-page: https://github.com/erkghlerngm44/aniffinity
Author: erkghlerngm44
Author-email: erkghlerngm44@protonmail.com
License: MIT
Keywords: anilist affinity kitsu myanimelist scores pearson
Platform: UNKNOWN
Classifier: Development Status :: 4 - Beta
Classifier: Intended Audience :: Developers
Classifier: Topic :: Software Development
Classifier: Operating System :: OS Independent
Classifier: License :: OSI Approved :: MIT License
Classifier: Programming Language :: Python :: 3
Classifier: Programming Language :: Python :: 3.4
Classifier: Programming Language :: Python :: 3.5
Classifier: Programming Language :: Python :: 3.6
Classifier: Programming Language :: Python :: 3.7
Requires-Dist: json-api-doc (<0.8,>=0.7)
Requires-Dist: requests (<3,>=2.18)
Provides-Extra: conventions
Requires-Dist: flake8 (<4,>=3.4) ; extra == 'conventions'
Requires-Dist: pydocstyle (<4,>=3.0) ; extra == 'conventions'
Provides-Extra: docs
Requires-Dist: sphinx (<2,>=1.6) ; extra == 'docs'
Requires-Dist: sphinx-rtd-theme ; extra == 'docs'
Provides-Extra: tests
Requires-Dist: coverage (<5,>=4.4) ; extra == 'tests'
Requires-Dist: mock (<3,>=2.0) ; extra == 'tests'
Requires-Dist: pytest (<5,>=4.1) ; extra == 'tests'
Requires-Dist: vcrpy (<3,>=2.0) ; extra == 'tests'
Provides-Extra: travis
Requires-Dist: codecov (<3,>=2.0) ; extra == 'travis'
